README
setup.cfg
setup.py
marketopythonrest/__init__.py
marketopythonrest/client.py
marketopythonrest.egg-info/PKG-INFO
marketopythonrest.egg-info/SOURCES.txt
marketopythonrest.egg-info/dependency_links.txt
marketopythonrest.egg-info/requires.txt
marketopythonrest.egg-info/top_level.txt
marketopythonrest/helper/__init__.py
marketopythonrest/helper/exceptions.py
marketopythonrest/helper/http_lib.py