Metadata-Version: 1.0
Name: marketopythonrest
Version: 0.1.1
Summary: Python Client for the Marketo REST API
Home-page: https://github.com/jepcastelein/marketo-rest-python
Author: Jep Castelein
Author-email: jep@castelein.net
License: MIT License
Keywords: Marketo,REST API,Wrapper,Client
Platform: UNKNOWN
